sri_tpot/__init__.py
sri_tpot/_version.py
sri_tpot/base.py
sri_tpot/decorators.py
sri_tpot/driver.py
sri_tpot/export_utils.py
sri_tpot/gp_deap.py
sri_tpot/gp_types.py
sri_tpot/metrics.py
sri_tpot/operator_utils.py
sri_tpot/tpot.py
sri_tpot/builtins/__init__.py
sri_tpot/builtins/combine_dfs.py
sri_tpot/builtins/one_hot_encoder.py
sri_tpot/builtins/stacking_estimator.py
sri_tpot/builtins/zero_count.py
sri_tpot/config/__init__.py
sri_tpot/config/classifier.py
sri_tpot/config/regressor.py
sri_tpot-1.3.0.dist-info/DESCRIPTION.rst
sri_tpot-1.3.0.dist-info/METADATA
sri_tpot-1.3.0.dist-info/RECORD
sri_tpot-1.3.0.dist-info/WHEEL
sri_tpot-1.3.0.dist-info/entry_points.txt
sri_tpot-1.3.0.dist-info/metadata.json
sri_tpot-1.3.0.dist-info/top_level.txt
sri_tpot-1.3.0.dist-info/zip-safe
